oops_wsgi/__init__.py
oops_wsgi/django.py
oops_wsgi/hooks.py
oops_wsgi/middleware.py
oops_wsgi-0.1.0.dist-info/licenses/LICENSE
oops_wsgi-0.1.0.dist-info/METADATA
oops_wsgi-0.1.0.dist-info/WHEEL
oops_wsgi-0.1.0.dist-info/top_level.txt
oops_wsgi-0.1.0.dist-info/RECORD
