Metadata-Version: 2.4
Name: oops_wsgi
Version: 0.1.0
Summary: OOPS wsgi middleware.
Home-page: https://launchpad.net/python-oops-wsgi
Maintainer: Launchpad Developers
Maintainer-email: launchpad-dev@lists.launchpad.net
Classifier: Development Status :: 2 - Pre-Alpha
Classifier: Intended Audience :: Developers
Classifier: License :: OSI Approved :: GNU Library or Lesser General Public License (LGPL)
Classifier: Operating System :: OS Independent
Classifier: Programming Language :: Python
Classifier: Programming Language :: Python :: 3
Classifier: Programming Language :: Python :: 3.8
License-File: LICENSE
Requires-Dist: oops
Provides-Extra: test
Requires-Dist: testtools; extra == "test"
Dynamic: classifier
Dynamic: description
Dynamic: description-content-type
Dynamic: home-page
Dynamic: license-file
Dynamic: maintainer
Dynamic: maintainer-email
Dynamic: provides-extra
Dynamic: requires-dist
Dynamic: summary
